ln_markets-2.0.11.dist-info/licenses/LICENSE
lnmarkets/__init__.py
lnmarkets/rest.py
lnmarkets/websockets.py
ln_markets-2.0.11.dist-info/METADATA
ln_markets-2.0.11.dist-info/WHEEL
ln_markets-2.0.11.dist-info/top_level.txt
ln_markets-2.0.11.dist-info/RECORD
