Metadata-Version: 2.4
Name: ln-markets
Version: 2.0.11
Summary: LN Markets API python implementation
Author: Romain ROUPHAEL
License-Expression: MIT
Project-URL: Homepage, https://github.com/ln-markets/api-python
Keywords: lnmarkets,trading,rest,api,bitcoin,lightning,network,futures,options
Classifier: Intended Audience :: Developers
Classifier: Operating System :: OS Independent
Classifier: Programming Language :: Python :: 3
Classifier: Programming Language :: Python :: 3.5
Classifier: Programming Language :: Python :: 3.6
Classifier: Programming Language :: Python :: 3.7
Classifier: Programming Language :: Python :: 3.8
Classifier: Programming Language :: Python
Classifier: Topic :: Software Development :: Libraries :: Python Modules
License-File: LICENSE
Requires-Dist: requests
Requires-Dist: websocket-client
Dynamic: license-file
